proxyspy.py
proxyspy-0.1.5.dist-info/METADATA
proxyspy-0.1.5.dist-info/WHEEL
proxyspy-0.1.5.dist-info/entry_points.txt
proxyspy-0.1.5.dist-info/licenses/LICENSE.txt
proxyspy-0.1.5.dist-info/RECORD
