Metadata-Version: 2.4
Name: proxyspy
Version: 0.1.5
Summary: A debugging proxy that can log or intercept HTTPS requests
Project-URL: Homepage, https://github.com/anaconda/proxyspy
Project-URL: Repository, https://github.com/anaconda/proxyspy
Author-email: "Anaconda, Inc." <conda@anaconda.com>
License: BSD 3-Clause License
License-File: LICENSE.txt
Classifier: Development Status :: 4 - Beta
Classifier: Intended Audience :: Developers
Classifier: License :: OSI Approved :: BSD License
Classifier: Operating System :: OS Independent
Classifier: Programming Language :: Python :: 3
Classifier: Programming Language :: Python :: 3.8
Classifier: Programming Language :: Python :: 3.9
Classifier: Programming Language :: Python :: 3.10
Classifier: Programming Language :: Python :: 3.11
Classifier: Programming Language :: Python :: 3.12
Classifier: Topic :: Internet :: Proxy Servers
Classifier: Topic :: Internet :: WWW/HTTP
Classifier: Topic :: Software Development :: Testing
Requires-Python: >=3.8
Requires-Dist: cryptography
Provides-Extra: test
Requires-Dist: psutil; extra == 'test'
Requires-Dist: pytest; extra == 'test'
Requires-Dist: requests; extra == 'test'
